stopwords/__init__.py
stopwords/_stopwords.py
stopwords/clis/README.md
stopwords/clis/__init__.py
stopwords/clis/cli.py
stopwords/data/stopwords.zh.all.txt
stopwords/data/stopwords.zh.baidu.txt
stopwords/data/stopwords.zh.cn.txt
stopwords/data/stopwords.zh.en.txt
stopwords/data/stopwords.zh.hit.txt
stopwords/data/stopwords.zh.ict.txt
stopwords/data/stopwords.zh.iso.txt
stopwords/data/stopwords.zh.marimo.txt
stopwords/data/stopwords.zh.scu.txt
stopwords_zh-2023.6.5.13.18.38.dist-info/LICENSE
stopwords_zh-2023.6.5.13.18.38.dist-info/METADATA
stopwords_zh-2023.6.5.13.18.38.dist-info/WHEEL
stopwords_zh-2023.6.5.13.18.38.dist-info/entry_points.txt
stopwords_zh-2023.6.5.13.18.38.dist-info/top_level.txt
stopwords_zh-2023.6.5.13.18.38.dist-info/RECORD
