Metadata-Version: 2.1
Name: stopwords-zh
Version: 2023.6.5.13.18.38
Summary: stopwords-zh
Home-page: https://github.com/yuanjie-ai/stopwords-zh
Author: stopwords-zh
Author-email: yuanjie@example.com
License: MIT license
Keywords: stopwords-zh
Classifier: Development Status :: 2 - Pre-Alpha
Classifier: Intended Audience :: Developers
Classifier: License :: OSI Approved :: MIT License
Classifier: Natural Language :: English
Classifier: Programming Language :: Python :: 3
Classifier: Programming Language :: Python :: 3.6
Classifier: Programming Language :: Python :: 3.7
Classifier: Programming Language :: Python :: 3.8
Requires-Python: >=3.6
License-File: LICENSE
